kinetics_kalculator/__init__.py
kinetics_kalculator/kinetics_kalculator.py
kinetics_kalculator/utils.py
kinetics_kalculator-0.1.0.dist-info/METADATA
kinetics_kalculator-0.1.0.dist-info/WHEEL
kinetics_kalculator-0.1.0.dist-info/licenses/LICENSE
kinetics_kalculator-0.1.0.dist-info/RECORD
