Metadata-Version: 2.3
Name: kinetics_kalculator
Version: 0.1.0
Project-URL: Homepage, https://github.com/nscorley/kinetics-kalculator
Author-email: Nathaniel Corley <nscorley@gmail.com>
License: MIT License
Requires-Python: >=3.8
Requires-Dist: matplotlib
Requires-Dist: numpy
Requires-Dist: pandas
Requires-Dist: rich
Requires-Dist: scipy
Requires-Dist: seaborn
